platypi/__init__.py
platypi/_base_client.py
platypi/_client.py
platypi/_compat.py
platypi/_constants.py
platypi/_exceptions.py
platypi/_files.py
platypi/_models.py
platypi/_qs.py
platypi/_resource.py
platypi/_response.py
platypi/_streaming.py
platypi/_types.py
platypi/_version.py
platypi/py.typed
platypi/_utils/__init__.py
platypi/_utils/_compat.py
platypi/_utils/_datetime_parse.py
platypi/_utils/_logs.py
platypi/_utils/_proxy.py
platypi/_utils/_reflection.py
platypi/_utils/_resources_proxy.py
platypi/_utils/_streams.py
platypi/_utils/_sync.py
platypi/_utils/_transform.py
platypi/_utils/_typing.py
platypi/_utils/_utils.py
platypi/lib/.keep
platypi/resources/__init__.py
platypi/resources/assistants.py
platypi/resources/audio.py
platypi/resources/batches.py
platypi/resources/completions.py
platypi/resources/embeddings.py
platypi/resources/files.py
platypi/resources/images.py
platypi/resources/models.py
platypi/resources/moderations.py
platypi/resources/realtime.py
platypi/resources/responses.py
platypi/resources/uploads.py
platypi/resources/chat/__init__.py
platypi/resources/chat/chat.py
platypi/resources/chat/completions.py
platypi/resources/containers/__init__.py
platypi/resources/containers/containers.py
platypi/resources/containers/files.py
platypi/resources/conversations/__init__.py
platypi/resources/conversations/conversations.py
platypi/resources/conversations/items.py
platypi/resources/evals/__init__.py
platypi/resources/evals/evals.py
platypi/resources/evals/runs/__init__.py
platypi/resources/evals/runs/output_items.py
platypi/resources/evals/runs/runs.py
platypi/resources/fine_tuning/__init__.py
platypi/resources/fine_tuning/fine_tuning.py
platypi/resources/fine_tuning/alpha/__init__.py
platypi/resources/fine_tuning/alpha/alpha.py
platypi/resources/fine_tuning/alpha/graders.py
platypi/resources/fine_tuning/checkpoints/__init__.py
platypi/resources/fine_tuning/checkpoints/checkpoints.py
platypi/resources/fine_tuning/checkpoints/permissions.py
platypi-1.0.0.dist-info/METADATA
platypi-1.0.0.dist-info/WHEEL
platypi-1.0.0.dist-info/licenses/LICENSE
platypi-1.0.0.dist-info/RECORD
